{"__class__": "MusicPlayer", "__module__": "musicbot.player", "data": {"current_entry": {"entry": {"__class__": "URLPlaylistEntry", "__module__": "musicbot.entry", "data": {"aoptions": "-vn", "downloaded": true, "duration": 188, "expected_filename": "audio_cache\\youtube-7VY191_NiHA-Nannaku_Prematho_Title_Song_Full_Video_Jr.NTR_Rakul_Preeet_Singh_DSP.webm", "filename": "audio_cache\\youtube-7VY191_NiHA-Nannaku_Prematho_Title_Song_Full_Video_Jr.NTR_Rakul_Preeet_Singh_DSP.webm", "full_filename": "C:\\Users\\bittu\\Desktop\\MusicBot-master\\New folder\\MusicBot\\audio_cache\\youtube-7VY191_NiHA-Nannaku_Prematho_Title_Song_Full_Video_Jr.NTR_Rakul_Preeet_Singh_DSP.webm", "meta": {"author": {"id": 383315939816505351, "name": "BittuCNGT YT", "type": "Member"}, "channel": {"id": 474395995313012743, "name": "commands", "type": "TextChannel"}}, "title": "Nannaku Prematho Title Song Full Video | Jr.NTR | Rakul Preeet Singh | DSP", "url": "https://www.youtube.com/watch?v=7VY191_NiHA", "version": 1}}, "progress": 0, "progress_frames": 1}, "entries": {"__class__": "Playlist", "__module__": "musicbot.playlist", "data": {"entries": []}}}}